harmonify/__init__.py
harmonify/context.py
harmonify/core.py
harmonify/flow_control.py
harmonify/func_types.py
harmonify/handler.py
harmonify/hook.py
harmonify/info_utils.py
harmonify/patch.py
harmonify/injector/__init__.py
harmonify/injector/core.py
harmonify/injector/security.py
harmonify/injector/utils.py
harmonify_patcher-3.1.2.dist-info/licenses/LICENSE
harmonify_patcher-3.1.2.dist-info/METADATA
harmonify_patcher-3.1.2.dist-info/WHEEL
harmonify_patcher-3.1.2.dist-info/top_level.txt
harmonify_patcher-3.1.2.dist-info/RECORD
