Metadata-Version: 2.4
Name: harmonify-patcher
Version: 3.1.2
Summary: Method behavior modification at runtime, made easy.
Author-email: Wind Rider <abcbcalol69@gmail.com>
License: MIT License
Project-URL: Homepage, https://github.com/ProgrammingLover71/Harmonify
Keywords: patcher,python,library
Classifier: License :: OSI Approved :: MIT License
Classifier: Programming Language :: Python
Classifier: Programming Language :: Python :: 3
Requires-Python: >=3.10
License-File: LICENSE
Dynamic: license-file
